blam3sdk/__init__.py
blam3sdk/blamclient.py
blam3sdk/blidget.py
blam3sdk/blidgetoutput.py
blam3sdk/runconfig.py
blam3sdk/tokengenerator.py
blam3sdk/workflowio.py
blam3sdk/blam/__init__.py
blam3sdk/blam/enums.py
blam3sdk/blam/extensions.py
blam3sdk-0.0.1.dist-info/LICENSE
blam3sdk-0.0.1.dist-info/METADATA
blam3sdk-0.0.1.dist-info/WHEEL
blam3sdk-0.0.1.dist-info/top_level.txt
blam3sdk-0.0.1.dist-info/RECORD
