Metadata-Version: 2.1
Name: blam3sdk
Version: 0.0.1
Summary: SDK for BLAM3 blidgets
Home-page: https://www.bluelucy.com
Author: Blue Lucy Media Ltd.
Author-email: support@bluelucy.com
License: UNKNOWN
Platform: UNKNOWN
Classifier: Programming Language :: Python :: 3
Classifier: License :: OSI Approved :: MIT License
Classifier: Operating System :: OS Independent
Requires-Python: >=3.7
